react_agent_framework/__init__.py
react_agent_framework/cli/__init__.py
react_agent_framework/cli/app.py
react_agent_framework/core/__init__.py
react_agent_framework/core/react_agent.py
react_agent_framework/core/environment/__init__.py
react_agent_framework/core/environment/base.py
react_agent_framework/core/environment/cli.py
react_agent_framework/core/environment/file.py
react_agent_framework/core/environment/web.py
react_agent_framework/core/memory/__init__.py
react_agent_framework/core/memory/adapters.py
react_agent_framework/core/memory/base.py
react_agent_framework/core/memory/chroma.py
react_agent_framework/core/memory/faiss.py
react_agent_framework/core/memory/simple.py
react_agent_framework/core/memory/chat/__init__.py
react_agent_framework/core/memory/chat/base.py
react_agent_framework/core/memory/chat/simple.py
react_agent_framework/core/memory/chat/sqlite.py
react_agent_framework/core/memory/knowledge/__init__.py
react_agent_framework/core/memory/knowledge/base.py
react_agent_framework/core/memory/knowledge/chroma.py
react_agent_framework/core/memory/knowledge/faiss.py
react_agent_framework/core/objectives/__init__.py
react_agent_framework/core/objectives/objective.py
react_agent_framework/core/objectives/tracker.py
react_agent_framework/core/reasoning/__init__.py
react_agent_framework/core/reasoning/base.py
react_agent_framework/core/reasoning/plan_execute.py
react_agent_framework/core/reasoning/react.py
react_agent_framework/core/reasoning/reflection.py
react_agent_framework/core/reasoning/rewoo.py
react_agent_framework/examples/__init__.py
react_agent_framework/examples/builtin_tools.py
react_agent_framework/examples/custom_tools.py
react_agent_framework/examples/fastapi_style.py
react_agent_framework/examples/infrastructure_cost_control_demo.py
react_agent_framework/examples/infrastructure_human_loop_demo.py
react_agent_framework/examples/infrastructure_monitoring_demo.py
react_agent_framework/examples/infrastructure_resilience_demo.py
react_agent_framework-0.12.0.dist-info/licenses/LICENSE
react_agent_framework-0.12.0.dist-info/METADATA
react_agent_framework-0.12.0.dist-info/WHEEL
react_agent_framework-0.12.0.dist-info/entry_points.txt
react_agent_framework-0.12.0.dist-info/top_level.txt
react_agent_framework-0.12.0.dist-info/RECORD
