Metadata-Version: 2.4
Name: react-agent-framework
Version: 0.12.0
Summary: Production-ready AI agent framework with multi-agent systems (Layer 3), complete infrastructure (Layer 4), MCP support, environments, reasoning strategies, objectives, memory, and built-in tools
Author-email: Marcos <marcosf63@gmail.com>
License: MIT
Project-URL: Homepage, https://marcosf63.github.io/react-agent-framework/
Project-URL: Documentation, https://marcosf63.github.io/react-agent-framework/
Project-URL: Repository, https://github.com/marcosf63/react-agent-framework
Project-URL: Issues, https://github.com/marcosf63/react-agent-framework/issues
Keywords: ai,agent,react,llm,openai,framework
Classifier: Development Status :: 3 - Alpha
Classifier: Intended Audience :: Developers
Classifier: License :: OSI Approved :: MIT License
Classifier: Programming Language :: Python :: 3
Classifier: Programming Language :: Python :: 3.8
Classifier: Programming Language :: Python :: 3.9
Classifier: Programming Language :: Python :: 3.10
Classifier: Programming Language :: Python :: 3.11
Classifier: Programming Language :: Python :: 3.12
Classifier: Topic :: Software Development :: Libraries :: Application Frameworks
Classifier: Topic :: Scientific/Engineering :: Artificial Intelligence
Requires-Python: >=3.9
License-File: LICENSE
Requires-Dist: openai>=1.0.0
Requires-Dist: python-dotenv>=1.0.0
Requires-Dist: duckduckgo-search>=4.0.0
Requires-Dist: typer>=0.9.0
Requires-Dist: rich>=13.0.0
Requires-Dist: requests>=2.31.0
Provides-Extra: mcp
Requires-Dist: mcp>=1.0.0; extra == "mcp"
Provides-Extra: anthropic
Requires-Dist: anthropic>=0.18.0; extra == "anthropic"
Provides-Extra: google
Requires-Dist: google-generativeai>=0.3.0; extra == "google"
Provides-Extra: all-providers
Requires-Dist: anthropic>=0.18.0; extra == "all-providers"
Requires-Dist: google-generativeai>=0.3.0; extra == "all-providers"
Provides-Extra: search
Requires-Dist: duckduckgo-search>=4.0.0; extra == "search"
Provides-Extra: computation
Provides-Extra: filesystem
Provides-Extra: all-tools
Requires-Dist: duckduckgo-search>=4.0.0; extra == "all-tools"
Provides-Extra: chat-sqlite
Provides-Extra: chat-postgres
Requires-Dist: psycopg2-binary>=2.9.0; extra == "chat-postgres"
Provides-Extra: all-chat
Requires-Dist: psycopg2-binary>=2.9.0; extra == "all-chat"
Provides-Extra: knowledge-chroma
Requires-Dist: chromadb>=0.4.0; extra == "knowledge-chroma"
Provides-Extra: knowledge-faiss
Requires-Dist: faiss-cpu>=1.7.4; extra == "knowledge-faiss"
Requires-Dist: numpy>=1.24.0; extra == "knowledge-faiss"
Provides-Extra: all-knowledge
Requires-Dist: chromadb>=0.4.0; extra == "all-knowledge"
Requires-Dist: faiss-cpu>=1.7.4; extra == "all-knowledge"
Requires-Dist: numpy>=1.24.0; extra == "all-knowledge"
Provides-Extra: memory-chroma
Requires-Dist: chromadb>=0.4.0; extra == "memory-chroma"
Provides-Extra: memory-faiss
Requires-Dist: faiss-cpu>=1.7.4; extra == "memory-faiss"
Requires-Dist: numpy>=1.24.0; extra == "memory-faiss"
Provides-Extra: all-memory
Requires-Dist: chromadb>=0.4.0; extra == "all-memory"
Requires-Dist: faiss-cpu>=1.7.4; extra == "all-memory"
Requires-Dist: numpy>=1.24.0; extra == "all-memory"
Requires-Dist: psycopg2-binary>=2.9.0; extra == "all-memory"
Provides-Extra: all
Requires-Dist: anthropic>=0.18.0; extra == "all"
Requires-Dist: google-generativeai>=0.3.0; extra == "all"
Requires-Dist: chromadb>=0.4.0; extra == "all"
Requires-Dist: faiss-cpu>=1.7.4; extra == "all"
Requires-Dist: numpy>=1.24.0; extra == "all"
Requires-Dist: psycopg2-binary>=2.9.0; extra == "all"
Requires-Dist: mcp>=1.0.0; extra == "all"
Provides-Extra: dev
Requires-Dist: pytest>=7.0.0; extra == "dev"
Requires-Dist: pytest-cov>=4.0.0; extra == "dev"
Requires-Dist: black>=23.0.0; extra == "dev"
Requires-Dist: ruff>=0.1.0; extra == "dev"
Requires-Dist: mypy>=1.0.0; extra == "dev"
Dynamic: license-file
